motor/__init__.py
motor/_version.py
motor/core.py
motor/core.pyi
motor/docstrings.py
motor/metaprogramming.py
motor/motor_asyncio.py
motor/motor_asyncio.pyi
motor/motor_common.py
motor/motor_gridfs.py
motor/motor_gridfs.pyi
motor/motor_tornado.py
motor/motor_tornado.pyi
motor/py.typed
motor/web.py
motor/aiohttp/__init__.py
motor/frameworks/__init__.py
motor/frameworks/asyncio/__init__.py
motor/frameworks/tornado/__init__.py
motor-3.4.0.dist-info/LICENSE
motor-3.4.0.dist-info/METADATA
motor-3.4.0.dist-info/WHEEL
motor-3.4.0.dist-info/top_level.txt
motor-3.4.0.dist-info/RECORD
