Metadata-Version: 2.1
Name: motor
Version: 3.4.0
Summary: Non-blocking MongoDB driver for Tornado or asyncio
Author-email: "A. Jesse Jiryu Davis" <jesse@mongodb.com>
License:                                  Apache License
Project-URL: Homepage, https://www.mongodb.org
Project-URL: Documentation, https://motor.readthedocs.io
Project-URL: Source, https://github.com/mongodb/motor
Project-URL: Tracker, https://jira.mongodb.org/projects/MOTOR/issues
Keywords: asyncio,bson,gridfs,mongo,mongodb,motor,pymongo,tornado
Classifier: Development Status :: 5 - Production/Stable
Classifier: Intended Audience :: Developers
Classifier: License :: OSI Approved :: Apache Software License
Classifier: Natural Language :: English
Classifier: Operating System :: MacOS :: MacOS X
Classifier: Operating System :: Microsoft :: Windows
Classifier: Operating System :: Unix
Classifier: Typing :: Typed
Classifier: Programming Language :: Python
Classifier: Programming Language :: Python :: 3
Classifier: Programming Language :: Python :: 3.7
Classifier: Programming Language :: Python :: 3.8
Classifier: Programming Language :: Python :: 3.9
Classifier: Programming Language :: Python :: Implementation :: CPython
Classifier: Programming Language :: Python :: Implementation :: PyPy
Classifier: Programming Language :: Python :: 3.10
Classifier: Programming Language :: Python :: 3.11
Classifier: Programming Language :: Python :: 3.12
Requires-Python: >=3.7
License-File: LICENSE
Requires-Dist: pymongo<5,>=4.5
Provides-Extra: aws
Requires-Dist: pymongo[aws]<5,>=4.5; extra == "aws"
Provides-Extra: encryption
Requires-Dist: pymongo[encryption]<5,>=4.5; extra == "encryption"
Provides-Extra: gssapi
Requires-Dist: pymongo[gssapi]<5,>=4.5; extra == "gssapi"
Provides-Extra: ocsp
Requires-Dist: pymongo[ocsp]<5,>=4.5; extra == "ocsp"
Provides-Extra: snappy
Requires-Dist: pymongo[snappy]<5,>=4.5; extra == "snappy"
Provides-Extra: srv
Requires-Dist: pymongo[srv]<5,>=4.5; extra == "srv"
Provides-Extra: test
Requires-Dist: pytest>=7; extra == "test"
Requires-Dist: mockupdb; extra == "test"
Requires-Dist: tornado>=5; extra == "test"
Requires-Dist: aiohttp!=3.8.6; extra == "test"
Requires-Dist: motor[encryption]; extra == "test"
Provides-Extra: zstd
Requires-Dist: pymongo[zstd]<5,>=4.5; extra == "zstd"
